ChangeLog
MANIFEST.in
README
setup.cfg
setup.py
IrssiNotifier.egg-info/PKG-INFO
IrssiNotifier.egg-info/SOURCES.txt
IrssiNotifier.egg-info/dependency_links.txt
IrssiNotifier.egg-info/entry_points.txt
IrssiNotifier.egg-info/not-zip-safe
IrssiNotifier.egg-info/top_level.txt
irssinotifier/__init__.py
irssinotifier/irssi_mini.png
irssinotifier/notifier.py
irssinotifier/parser.py
