Metadata-Version: 1.0
Name: IrssiNotifier
Version: 0.1.1
Summary: Irssi Real Time Remote Visual Notification.
Home-page: http://blog.ufsoft.org/index.php/category/irssi-notification/
Author: Pedro Algarvio
Author-email: ufs@ufsoft.org
License: BSD
Keywords: irssi,visual notification,notification
Platform: Anywere libnotify and python is known to run
Classifier: Development Status :: 3 - Alpha
Classifier: Environment :: X11 Applications
Classifier: Intended Audience :: End Users/Desktop
Classifier: License :: OSI Approved :: BSD License
Classifier: Natural Language :: English
Classifier: Operating System :: POSIX :: Linux
Classifier: Programming Language :: Python
Classifier: Topic :: Communications :: Chat :: Internet Relay Chat
Classifier: Topic :: Desktop Environment
Classifier: Topic :: Utilities
